nonebot_plugin_warframe/__init__.py
nonebot_plugin_warframe/data_source.py
nonebot_plugin_warframe-0.0.5.dist-info/LICENSE
nonebot_plugin_warframe-0.0.5.dist-info/METADATA
nonebot_plugin_warframe-0.0.5.dist-info/WHEEL
nonebot_plugin_warframe-0.0.5.dist-info/top_level.txt
nonebot_plugin_warframe-0.0.5.dist-info/RECORD
