Metadata-Version: 2.1
Name: nonebot-plugin-warframe
Version: 0.0.5
Summary: 基于NoneBot的星际战甲事件查询插件
Home-page: https://github.com/17TheWord/nonebot-plugin-warframe
Author: 17TheWord
Author-email: 17theword@gmail.com
License: UNKNOWN
Platform: UNKNOWN
Classifier: Programming Language :: Python :: 3.10
Classifier: License :: OSI Approved :: GNU Affero General Public License v3
Classifier: Operating System :: OS Independent
License-File: LICENSE
Requires-Dist: nonebot2 (>=2.0.0b4)
Requires-Dist: nonebot-adapter-onebot (>=2.1.1)
Requires-Dist: nonebot-plugin-guild-patch (>=0.2.0)
Requires-Dist: httpx (>=0.23.1)
